heifip/__init__.py
heifip/cli.py
heifip/extractor.py
heifip/main.py
heifip/splitter.py
heifip/exceptions/__init__.py
heifip/images/__init__.py
heifip/images/flow.py
heifip/images/flow_tiled_auto.py
heifip/images/flow_tiled_fixed.py
heifip/images/markovchain.py
heifip/images/packet.py
heifip/layers/__init__.py
heifip/layers/dns.py
heifip/layers/http.py
heifip/layers/ip.py
heifip/layers/packet.py
heifip/layers/ssh.py
heifip/layers/transport.py
heifip/plugins/__init__.py
heifip/plugins/header.py
heifip/protocols/__init__.py
heifip/protocols/ssh.py
heifip-1.1.1.dist-info/LICENSE
heifip-1.1.1.dist-info/METADATA
heifip-1.1.1.dist-info/WHEEL
heifip-1.1.1.dist-info/entry_points.txt
heifip-1.1.1.dist-info/top_level.txt
heifip-1.1.1.dist-info/RECORD
