Metadata-Version: 2.1
Name: heifip
Version: 1.1.1
Summary: A tool to convert network traffic into images for ML use cases.
Author-email: Stefan Machmeier <stefan.machmeier@uni-heidelberg.de>
License: EUROPEAN UNION PUBLIC LICENCE v. 1.2
Project-URL: Homepage, https://github.com/stefanDeveloper/heiFIP
Project-URL: Bug Tracker, https://github.com/stefanDeveloper/heiFIP/issues
Keywords: network
Classifier: Programming Language :: Python :: 3
Classifier: License :: OSI Approved :: European Union Public Licence 1.2 (EUPL 1.2)
Classifier: Operating System :: OS Independent
Classifier: Operating System :: OS Independent
Classifier: Intended Audience :: Telecommunications Industry
Classifier: Intended Audience :: Information Technology
Classifier: Intended Audience :: System Administrators
Classifier: Intended Audience :: Science/Research
Classifier: Intended Audience :: Developers
Classifier: Programming Language :: Python :: 3 :: Only
Classifier: Programming Language :: Python :: 3.7
Classifier: Programming Language :: Python :: 3.8
Classifier: Programming Language :: Python :: 3.9
Classifier: Programming Language :: Python :: 3.10
Classifier: Programming Language :: Python :: 3.11
Classifier: Topic :: Security
Classifier: Topic :: Internet :: Log Analysis
Classifier: Topic :: System :: Networking :: Monitoring
Classifier: Topic :: Scientific/Engineering :: Artificial Intelligence
Requires-Python: >=3.7
License-File: LICENSE
